32word-0.2.1.dist-info/licenses/LICENSE
word32/__init__.py
word32/config.py
word32/core.py
word32/data_loader.py
word32/data_manager.py
word32/exceptions.py
word32/response_schema.py
word32/strategy.py
word32/data/phase2_naive_32.json
word32/data/phase3_lookup.json
word32/data/targets.txt
word32/data/v1.0.json
word32/data/valid_guesses.txt
word32/data/strategies/2d_8r_adult.json
word32/data/strategies/2d_8r_crone.json
word32/data/strategies/2d_8r_dealt.json
word32/data/strategies/2d_8r_noise.json
word32/data/strategies/2d_8r_poser.json
word32/data/strategies/2d_8r_rinse.json
word32/data/strategies/2d_8r_risen.json
word32/data/strategies/2d_8r_salet.json
word32/data/strategies/2d_8r_salet_n3158_plus1.json
word32/data/strategies/2d_8r_siren.json
word32/data/strategies/2d_8r_snore.json
word32/data/strategies/2d_8r_trice.json
32word-0.2.1.dist-info/METADATA
32word-0.2.1.dist-info/WHEEL
32word-0.2.1.dist-info/top_level.txt
32word-0.2.1.dist-info/RECORD
