Metadata-Version: 2.4
Name: 32word
Version: 0.2.1
Summary: The game engine for 3-2-Word: Solve Wordle in three guesses. Includes standardized response schema (Phase 4.2), custom first guess selection from 32 optimal options (Phase 4.3), remaining words tracking, and comprehensive strategy lookup.
Author: Benjamin Mazzotta
License: MIT
Project-URL: Homepage, https://github.com/benmazzotta/32word
Project-URL: Repository, https://github.com/benmazzotta/32word
Project-URL: Issues, https://github.com/benmazzotta/32word/issues
Project-URL: Documentation, https://github.com/benmazzotta/32word/tree/main/docs
Keywords: wordle,game-engine,strategy,solver,word-puzzle
Classifier: Development Status :: 4 - Beta
Classifier: Programming Language :: Python :: 3
Classifier: Programming Language :: Python :: 3.8
Classifier: Programming Language :: Python :: 3.9
Classifier: Programming Language :: Python :: 3.10
Classifier: Programming Language :: Python :: 3.11
Classifier: Programming Language :: Python :: 3.12
Classifier: License :: OSI Approved :: MIT License
Classifier: Operating System :: OS Independent
Classifier: Intended Audience :: Developers
Classifier: Topic :: Games/Entertainment :: Puzzle Games
Classifier: Topic :: Software Development :: Libraries :: Python Modules
Requires-Python: >=3.8
License-File: LICENSE
Provides-Extra: dev
Requires-Dist: pytest>=7.0.0; extra == "dev"
Requires-Dist: pytest-cov>=4.0.0; extra == "dev"
Dynamic: license-file
